am_i_varun_or_yugandhar/__init__.py
am_i_varun_or_yugandhar/christmas.py
am_i_varun_or_yugandhar/conversation.py
am_i_varun_or_yugandhar/xmas.py
am_i_varun_or_yugandhar/xmas_turtle.py
am_i_varun_or_yughandar-0.1.dist-info/LICENCE.txt
am_i_varun_or_yughandar-0.1.dist-info/METADATA
am_i_varun_or_yughandar-0.1.dist-info/WHEEL
am_i_varun_or_yughandar-0.1.dist-info/top_level.txt
am_i_varun_or_yughandar-0.1.dist-info/RECORD
